Metadata-Version: 1.0
Name: udacity-cocajoey-dsnd
Version: 0.1
Summary: Gaussian and Binomial Distributions
Home-page: UNKNOWN
Author: Jing Zhang
Author-email: joeyzhang0401@gmail.com
License: UNKNOWN
Platform: UNKNOWN
